sc010/__init__.py
sc010/aspeed.py
sc010_controller-0.1.0.dist-info/licenses/LICENSE
sc010_controller-0.1.0.dist-info/METADATA
sc010_controller-0.1.0.dist-info/WHEEL
sc010_controller-0.1.0.dist-info/top_level.txt
sc010_controller-0.1.0.dist-info/RECORD
