Metadata-Version: 2.4
Name: sc010-controller
Version: 0.1.0
Summary: A Python library for controlling SC010 AV over IP controllers
Home-page: https://github.com/yourusername/sc010-controller
Author: Justin Faulk
Author-email: jfaulk@proitav.us
Classifier: Development Status :: 4 - Beta
Classifier: Intended Audience :: Developers
Classifier: License :: OSI Approved :: MIT License
Classifier: Operating System :: OS Independent
Classifier: Programming Language :: Python :: 3
Classifier: Programming Language :: Python :: 3.7
Classifier: Programming Language :: Python :: 3.8
Classifier: Programming Language :: Python :: 3.9
Classifier: Programming Language :: Python :: 3.10
Classifier: Topic :: Software Development :: Libraries :: Python Modules
Classifier: Topic :: Multimedia :: Video
Requires-Python: >=3.7
License-File: LICENSE
Requires-Dist: telnetlib3>=2.0.0
Dynamic: author
Dynamic: author-email
Dynamic: classifier
Dynamic: description
Dynamic: description-content-type
Dynamic: home-page
Dynamic: license-file
Dynamic: requires-dist
Dynamic: requires-python
Dynamic: summary
